Workbook

Sheet Mapping 
A1: Model_Row_Name | B1: Account | C1: Category | D1: Sign
A2: Subscription Revenue | B2: Subscription Revenue | C2: Revenue | D2: 1
A3: Expansion Revenue | B3: Expansion Revenue | C3: Revenue | D3: 1
A4: Total Revenue | B4: Total Revenue | C4: Revenue | D4: 1
A5: COGS | B5: COGS | C5: COGS | D5: -1
A6: Sales & Marketing | B6: Sales & Marketing Expense | C6: Opex | D6: -1
A7: R&D | B7: R&D Expense | C7: Opex | D7: -1
A8: G&A | B8: G&A Expense | C8: Opex | D8: -1
A9: Gross Profit | B9: Gross Profit | C9: Gross Profit | D9: 1
A10: EBTIDA | B10: EBTIDA | C10: EBTIDA | D10: 1

Sheet Budget_Import
A1: =IFERROR(__xludf.DUMMYFUNCTION("IMPORTRANGE(""https://docs.google.com/spreadsheets/d/18n6vxnIcwhgJ9zdCV0_b5v4IeoBYBlg3uhyGDpm3fnk/edit?gid=1111905003#gid=1111905003"",""Operating Model (P&L)!A34:AL44"")"),"Section F") -> Section F
A2: =IFERROR(__xludf.DUMMYFUNCTION("""COMPUTED_VALUE"""),"Subscription Revenue ") -> Subscription Revenue | B2: =IFERROR(__xludf.DUMMYFUNCTION("""COMPUTED_VALUE"""),464971.5) -> 464971.5 | C2: =IFERROR(__xludf.DUMMYFUNCTION("""COMPUTED_VALUE"""),468097.69999999995) -> 468097.7 | D2: =IFERROR(__xludf.DUMMYFUNCTION("""COMPUTED_VALUE"""),471152.85) -> 471152.85 | E2: =IFERROR(__xludf.DUMMYFUNCTION("""COMPUTED_VALUE"""),474208.0) -> 474208 | F2: =IFERROR(__xludf.DUMMYFUNCTION("""COMPUTED_VALUE"""),477192.1) -> 477192.1 | G2: =IFERROR(__xludf.DUMMYFUNCTION("""COMPUTED_VALUE"""),480034.1) -> 480034.1 | H2: =IFERROR(__xludf.DUMMYFUNCTION("""COMPUTED_VALUE"""),482855.80000000005) -> 482855.8 | I2: =IFERROR(__xludf.DUMMYFUNCTION("""COMPUTED_VALUE"""),485576.0) -> 485576 | J2: =IFERROR(__xludf.DUMMYFUNCTION("""COMPUTED_VALUE"""),488326.65) -> 488326.65 | K2: =IFERROR(__xludf.DUMMYFUNCTION("""COMPUTED_VALUE"""),490884.44999999995) -> 490884.45 | L2: =IFERROR(__xludf.DUMMYFUNCTION("""COMPUTED_VALUE"""),493513.30000000005) -> 493513.3 | M2: =IFERROR(__xludf.DUMMYFUNCTION("""COMPUTED_VALUE"""),496000.05000000005) -> 496000.05 | N2: =IFERROR(__xludf.DUMMYFUNCTION("""COMPUTED_VALUE"""),498486.80000000005) -> 498486.8 | O2: =IFERROR(__xludf.DUMMYFUNCTION("""COMPUTED_VALUE"""),500780.69999999995) -> 500780.7 | P2: =IFERROR(__xludf.DUMMYFUNCTION("""COMPUTED_VALUE"""),503125.35) -> 503125.35 | Q2: =IFERROR(__xludf.DUMMYFUNCTION("""COMPUTED_VALUE"""),505398.94999999995) -> 505398.95 | R2: =IFERROR(__xludf.DUMMYFUNCTION("""COMPUTED_VALUE"""),507723.30000000005) -> 507723.3 | S2: =IFERROR(__xludf.DUMMYFUNCTION("""COMPUTED_VALUE"""),509854.80000000005) -> 509854.8 | T2: =IFERROR(__xludf.DUMMYFUNCTION("""COMPUTED_VALUE"""),511986.30000000005) -> 511986.3 | U2: =IFERROR(__xludf.DUMMYFUNCTION("""COMPUTED_VALUE"""),513996.0) -> 513996 | V2: =IFERROR(__xludf.DUMMYFUNCTION("""COMPUTED_VALUE"""),516056.44999999995) -> 516056.45 | W2: =IFERROR(__xludf.DUMMYFUNCTION("""COMPUTED_VALUE"""),517974.80000000005) -> 517974.8 | X2: =IFERROR(__xludf.DUMMYFUNCTION("""COMPUTED_VALUE"""),520014.94999999995) -> 520014.95 | Y2: =IFERROR(__xludf.DUMMYFUNCTION("""COMPUTED_VALUE"""),521882.55000000005) -> 521882.55 | Z2: =IFERROR(__xludf.DUMMYFUNCTION("""COMPUTED_VALUE"""),523729.85000000003) -> 523729.85 | AA2: =IFERROR(__xludf.DUMMYFUNCTION("""COMPUTED_VALUE"""),525556.8500000001) -> 525556.85 | AB2: =IFERROR(__xludf.DUMMYFUNCTION("""COMPUTED_VALUE"""),527211.3) -> 527211.3 | AC2: =IFERROR(__xludf.DUMMYFUNCTION("""COMPUTED_VALUE"""),528987.55) -> 528987.55 | AD2: =IFERROR(__xludf.DUMMYFUNCTION("""COMPUTED_VALUE"""),530743.5) -> 530743.5 | AE2: =IFERROR(__xludf.DUMMYFUNCTION("""COMPUTED_VALUE"""),532377.6499999999) -> 532377.65 | AF2: =IFERROR(__xludf.DUMMYFUNCTION("""COMPUTED_VALUE"""),533961.05) -> 533961.05 | AG2: =IFERROR(__xludf.DUMMYFUNCTION("""COMPUTED_VALUE"""),535524.1499999999) -> 535524.15 | AH2: =IFERROR(__xludf.DUMMYFUNCTION("""COMPUTED_VALUE"""),537016.2) -> 537016.2 | AI2: =IFERROR(__xludf.DUMMYFUNCTION("""COMPUTED_VALUE"""),538559.0) -> 538559 | AJ2: =IFERROR(__xludf.DUMMYFUNCTION("""COMPUTED_VALUE"""),540051.05) -> 540051.05 | AK2: =IFERROR(__xludf.DUMMYFUNCTION("""COMPUTED_VALUE"""),541421.3) -> 541421.3 | AL2: =IFERROR(__xludf.DUMMYFUNCTION("""COMPUTED_VALUE"""),542842.3) -> 542842.3
A3: =IFERROR(__xludf.DUMMYFUNCTION("""COMPUTED_VALUE"""),"Total Revenue ") -> Total Revenue | B3: =IFERROR(__xludf.DUMMYFUNCTION("""COMPUTED_VALUE"""),488220.075) -> 488220.08 | C3: =IFERROR(__xludf.DUMMYFUNCTION("""COMPUTED_VALUE"""),491502.58499999996) -> 491502.59 | D3: =IFERROR(__xludf.DUMMYFUNCTION("""COMPUTED_VALUE"""),494710.4925) -> 494710.49 | E3: =IFERROR(__xludf.DUMMYFUNCTION("""COMPUTED_VALUE"""),497918.4) -> 497918.4 | F3: =IFERROR(__xludf.DUMMYFUNCTION("""COMPUTED_VALUE"""),501051.70499999996) -> 501051.71 | G3: =IFERROR(__xludf.DUMMYFUNCTION("""COMPUTED_VALUE"""),504035.805) -> 504035.8 | H3: =IFERROR(__xludf.DUMMYFUNCTION("""COMPUTED_VALUE"""),506998.59) -> 506998.59 | I3: =IFERROR(__xludf.DUMMYFUNCTION("""COMPUTED_VALUE"""),509854.8) -> 509854.8 | J3: =IFERROR(__xludf.DUMMYFUNCTION("""COMPUTED_VALUE"""),512742.98250000004) -> 512742.98 | K3: =IFERROR(__xludf.DUMMYFUNCTION("""COMPUTED_VALUE"""),515428.6724999999) -> 515428.67 | L3: =IFERROR(__xludf.DUMMYFUNCTION("""COMPUTED_VALUE"""),518188.965) -> 518188.97 | M3: =IFERROR(__xludf.DUMMYFUNCTION("""COMPUTED_VALUE"""),520800.05250000005) -> 520800.05 | N3: =IFERROR(__xludf.DUMMYFUNCTION("""COMPUTED_VALUE"""),523411.1400000001) -> 523411.14 | O3: =IFERROR(__xludf.DUMMYFUNCTION("""COMPUTED_VALUE"""),525819.735) -> 525819.73 | P3: =IFERROR(__xludf.DUMMYFUNCTION("""COMPUTED_VALUE"""),528281.6174999999) -> 528281.62 | Q3: =IFERROR(__xludf.DUMMYFUNCTION("""COMPUTED_VALUE"""),530668.8975) -> 530668.9 | R3: =IFERROR(__xludf.DUMMYFUNCTION("""COMPUTED_VALUE"""),533109.4650000001) -> 533109.46 | S3: =IFERROR(__xludf.DUMMYFUNCTION("""COMPUTED_VALUE"""),535347.54) -> 535347.54 | T3: =IFERROR(__xludf.DUMMYFUNCTION("""COMPUTED_VALUE"""),537585.615) -> 537585.61 | U3: =IFERROR(__xludf.DUMMYFUNCTION("""COMPUTED_VALUE"""),539695.8) -> 539695.8 | V3: =IFERROR(__xludf.DUMMYFUNCTION("""COMPUTED_VALUE"""),541859.2725) -> 541859.27 | W3: =IFERROR(__xludf.DUMMYFUNCTION("""COMPUTED_VALUE"""),543873.54) -> 543873.54 | X3: =IFERROR(__xludf.DUMMYFUNCTION("""COMPUTED_VALUE"""),546015.6975) -> 546015.7 | Y3: =IFERROR(__xludf.DUMMYFUNCTION("""COMPUTED_VALUE"""),547976.6775) -> 547976.68 | Z3: =IFERROR(__xludf.DUMMYFUNCTION("""COMPUTED_VALUE"""),549916.3425) -> 549916.34 | AA3: =IFERROR(__xludf.DUMMYFUNCTION("""COMPUTED_VALUE"""),551834.6925000001) -> 551834.69 | AB3: =IFERROR(__xludf.DUMMYFUNCTION("""COMPUTED_VALUE"""),553571.865) -> 553571.86 | AC3: =IFERROR(__xludf.DUMMYFUNCTION("""COMPUTED_VALUE"""),555436.9275) -> 555436.93 | AD3: =IFERROR(__xludf.DUMMYFUNCTION("""COMPUTED_VALUE"""),557280.675) -> 557280.68 | AE3: =IFERROR(__xludf.DUMMYFUNCTION("""COMPUTED_VALUE"""),558996.5324999999) -> 558996.53 | AF3: =IFERROR(__xludf.DUMMYFUNCTION("""COMPUTED_VALUE"""),560659.1025) -> 560659.1 | AG3: =IFERROR(__xludf.DUMMYFUNCTION("""COMPUTED_VALUE"""),562300.3574999999) -> 562300.36 | AH3: =IFERROR(__xludf.DUMMYFUNCTION("""COMPUTED_VALUE"""),563867.01) -> 563867.01 | AI3: =IFERROR(__xludf.DUMMYFUNCTION("""COMPUTED_VALUE"""),565486.95) -> 565486.95 | AJ3: =IFERROR(__xludf.DUMMYFUNCTION("""COMPUTED_VALUE"""),567053.6025) -> 567053.6 | AK3: =IFERROR(__xludf.DUMMYFUNCTION("""COMPUTED_VALUE"""),568492.365) -> 568492.36 | AL3: =IFERROR(__xludf.DUMMYFUNCTION("""COMPUTED_VALUE"""),569984.415) -> 569984.42
A5: =IFERROR(__xludf.DUMMYFUNCTION("""COMPUTED_VALUE"""),"Gross Margin ") -> Gross Margin | B5: =IFERROR(__xludf.DUMMYFUNCTION("""COMPUTED_VALUE"""),395225.775) -> 395225.78 | C5: =IFERROR(__xludf.DUMMYFUNCTION("""COMPUTED_VALUE"""),397883.045) -> 397883.04 | D5: =IFERROR(__xludf.DUMMYFUNCTION("""COMPUTED_VALUE"""),400479.9225) -> 400479.92 | E5: =IFERROR(__xludf.DUMMYFUNCTION("""COMPUTED_VALUE"""),403076.80000000005) -> 403076.8 | F5: =IFERROR(__xludf.DUMMYFUNCTION("""COMPUTED_VALUE"""),405613.285) -> 405613.28 | G5: =IFERROR(__xludf.DUMMYFUNCTION("""COMPUTED_VALUE"""),408028.985) -> 408028.98 | H5: =IFERROR(__xludf.DUMMYFUNCTION("""COMPUTED_VALUE"""),410427.43) -> 410427.43 | I5: =IFERROR(__xludf.DUMMYFUNCTION("""COMPUTED_VALUE"""),412739.6) -> 412739.6 | J5: =IFERROR(__xludf.DUMMYFUNCTION("""COMPUTED_VALUE"""),415077.6525) -> 415077.65 | K5: =IFERROR(__xludf.DUMMYFUNCTION("""COMPUTED_VALUE"""),417251.7824999999) -> 417251.78 | L5: =IFERROR(__xludf.DUMMYFUNCTION("""COMPUTED_VALUE"""),419486.305) -> 419486.3 | M5: =IFERROR(__xludf.DUMMYFUNCTION("""COMPUTED_VALUE"""),421600.04250000004) -> 421600.04 | N5: =IFERROR(__xludf.DUMMYFUNCTION("""COMPUTED_VALUE"""),423713.78) -> 423713.78 | O5: =IFERROR(__xludf.DUMMYFUNCTION("""COMPUTED_VALUE"""),425663.595) -> 425663.59 | P5: =IFERROR(__xludf.DUMMYFUNCTION("""COMPUTED_VALUE"""),427656.5474999999) -> 427656.55 | Q5: =IFERROR(__xludf.DUMMYFUNCTION("""COMPUTED_VALUE"""),429589.1075) -> 429589.11 | R5: =IFERROR(__xludf.DUMMYFUNCTION("""COMPUTED_VALUE"""),431564.80500000005) -> 431564.8 | S5: =IFERROR(__xludf.DUMMYFUNCTION("""COMPUTED_VALUE"""),433376.58) -> 433376.58 | T5: =IFERROR(__xludf.DUMMYFUNCTION("""COMPUTED_VALUE"""),435188.355) -> 435188.35 | U5: =IFERROR(__xludf.DUMMYFUNCTION("""COMPUTED_VALUE"""),436896.60000000003) -> 436896.6 | V5: =IFERROR(__xludf.DUMMYFUNCTION("""COMPUTED_VALUE"""),438647.9825) -> 438647.98 | W5: =IFERROR(__xludf.DUMMYFUNCTION("""COMPUTED_VALUE"""),440278.58) -> 440278.58 | X5: =IFERROR(__xludf.DUMMYFUNCTION("""COMPUTED_VALUE"""),442012.7075) -> 442012.71 | Y5: =IFERROR(__xludf.DUMMYFUNCTION("""COMPUTED_VALUE"""),443600.1675) -> 443600.17 | Z5: =IFERROR(__xludf.DUMMYFUNCTION("""COMPUTED_VALUE"""),445170.3725) -> 445170.37 | AA5: =IFERROR(__xludf.DUMMYFUNCTION("""COMPUTED_VALUE"""),446723.3225000001) -> 446723.32 | AB5: =IFERROR(__xludf.DUMMYFUNCTION("""COMPUTED_VALUE"""),448129.605) -> 448129.6 | AC5: =IFERROR(__xludf.DUMMYFUNCTION("""COMPUTED_VALUE"""),449639.4175) -> 449639.42 | AD5: =IFERROR(__xludf.DUMMYFUNCTION("""COMPUTED_VALUE"""),451131.97500000003) -> 451131.97 | AE5: =IFERROR(__xludf.DUMMYFUNCTION("""COMPUTED_VALUE"""),452521.0024999999) -> 452521 | AF5: =IFERROR(__xludf.DUMMYFUNCTION("""COMPUTED_VALUE"""),453866.8925) -> 453866.89 | AG5: =IFERROR(__xludf.DUMMYFUNCTION("""COMPUTED_VALUE"""),455195.52749999997) -> 455195.53 | AH5: =IFERROR(__xludf.DUMMYFUNCTION("""COMPUTED_VALUE"""),456463.77) -> 456463.77 | AI5: =IFERROR(__xludf.DUMMYFUNCTION("""COMPUTED_VALUE"""),457775.14999999997) -> 457775.15 | AJ5: =IFERROR(__xludf.DUMMYFUNCTION("""COMPUTED_VALUE"""),459043.3925) -> 459043.39 | AK5: =IFERROR(__xludf.DUMMYFUNCTION("""COMPUTED_VALUE"""),460208.105) -> 460208.1 | AL5: =IFERROR(__xludf.DUMMYFUNCTION("""COMPUTED_VALUE"""),461415.955) -> 461415.96
A6: =IFERROR(__xludf.DUMMYFUNCTION("""COMPUTED_VALUE"""),"Gross Margin %") -> Gross Margin % | B6: =IFERROR(__xludf.DUMMYFUNCTION("""COMPUTED_VALUE"""),0.8095238095238095) -> 0.80952381 | C6: =IFERROR(__xludf.DUMMYFUNCTION("""COMPUTED_VALUE"""),0.8095238095238095) -> 0.80952381 | D6: =IFERROR(__xludf.DUMMYFUNCTION("""COMPUTED_VALUE"""),0.8095238095238095) -> 0.80952381 | E6: =IFERROR(__xludf.DUMMYFUNCTION("""COMPUTED_VALUE"""),0.8095238095238095) -> 0.80952381 | F6: =IFERROR(__xludf.DUMMYFUNCTION("""COMPUTED_VALUE"""),0.8095238095238095) -> 0.80952381 | G6: =IFERROR(__xludf.DUMMYFUNCTION("""COMPUTED_VALUE"""),0.8095238095238095) -> 0.80952381 | H6: =IFERROR(__xludf.DUMMYFUNCTION("""COMPUTED_VALUE"""),0.8095238095238094) -> 0.80952381 | I6: =IFERROR(__xludf.DUMMYFUNCTION("""COMPUTED_VALUE"""),0.8095238095238095) -> 0.80952381 | J6: =IFERROR(__xludf.DUMMYFUNCTION("""COMPUTED_VALUE"""),0.8095238095238095) -> 0.80952381 | K6: =IFERROR(__xludf.DUMMYFUNCTION("""COMPUTED_VALUE"""),0.8095238095238094) -> 0.80952381 | L6: =IFERROR(__xludf.DUMMYFUNCTION("""COMPUTED_VALUE"""),0.8095238095238094) -> 0.80952381 | M6: =IFERROR(__xludf.DUMMYFUNCTION("""COMPUTED_VALUE"""),0.8095238095238095) -> 0.80952381 | N6: =IFERROR(__xludf.DUMMYFUNCTION("""COMPUTED_VALUE"""),0.8095238095238094) -> 0.80952381 | O6: =IFERROR(__xludf.DUMMYFUNCTION("""COMPUTED_VALUE"""),0.8095238095238095) -> 0.80952381 | P6: =IFERROR(__xludf.DUMMYFUNCTION("""COMPUTED_VALUE"""),0.8095238095238095) -> 0.80952381 | Q6: =IFERROR(__xludf.DUMMYFUNCTION("""COMPUTED_VALUE"""),0.8095238095238095) -> 0.80952381 | R6: =IFERROR(__xludf.DUMMYFUNCTION("""COMPUTED_VALUE"""),0.8095238095238095) -> 0.80952381 | S6: =IFERROR(__xludf.DUMMYFUNCTION("""COMPUTED_VALUE"""),0.8095238095238095) -> 0.80952381 | T6: =IFERROR(__xludf.DUMMYFUNCTION("""COMPUTED_VALUE"""),0.8095238095238095) -> 0.80952381 | U6: =IFERROR(__xludf.DUMMYFUNCTION("""COMPUTED_VALUE"""),0.8095238095238095) -> 0.80952381 | V6: =IFERROR(__xludf.DUMMYFUNCTION("""COMPUTED_VALUE"""),0.8095238095238095) -> 0.80952381 | ... Y6: =IFERROR(__xludf.DUMMYFUNCTION("""COMPUTED_VALUE"""),0.8095238095238095) -> 0.80952381 | Z6: =IFERROR(__xludf.DUMMYFUNCTION("""COMPUTED_VALUE"""),0.8095238095238094) -> 0.80952381 | AA6: =IFERROR(__xludf.DUMMYFUNCTION("""COMPUTED_VALUE"""),0.8095238095238095) -> 0.80952381 | AB6: =IFERROR(__xludf.DUMMYFUNCTION("""COMPUTED_VALUE"""),0.8095238095238095) -> 0.80952381 | AC6: =IFERROR(__xludf.DUMMYFUNCTION("""COMPUTED_VALUE"""),0.8095238095238095) -> 0.80952381 | AD6: =IFERROR(__xludf.DUMMYFUNCTION("""COMPUTED_VALUE"""),0.8095238095238095) -> 0.80952381 | AE6: =IFERROR(__xludf.DUMMYFUNCTION("""COMPUTED_VALUE"""),0.8095238095238095) -> 0.80952381 | AF6: =IFERROR(__xludf.DUMMYFUNCTION("""COMPUTED_VALUE"""),0.8095238095238095) -> 0.80952381 | AG6: =IFERROR(__xludf.DUMMYFUNCTION("""COMPUTED_VALUE"""),0.8095238095238095) -> 0.80952381 | AH6: =IFERROR(__xludf.DUMMYFUNCTION("""COMPUTED_VALUE"""),0.8095238095238095) -> 0.80952381 | ... AL6: =IFERROR(__xludf.DUMMYFUNCTION("""COMPUTED_VALUE"""),0.8095238095238095) -> 0.80952381
A8: =IFERROR(__xludf.DUMMYFUNCTION("""COMPUTED_VALUE"""),"Operating Income ") -> Operating Income | B8: =IFERROR(__xludf.DUMMYFUNCTION("""COMPUTED_VALUE"""),-648550.855) -> -648550.85 | C8: =IFERROR(__xludf.DUMMYFUNCTION("""COMPUTED_VALUE"""),-648457.0689999999) -> -648457.07 | D8: =IFERROR(__xludf.DUMMYFUNCTION("""COMPUTED_VALUE"""),-648365.4145000001) -> -648365.41 | E8: =IFERROR(__xludf.DUMMYFUNCTION("""COMPUTED_VALUE"""),-680273.76) -> -680273.76 | F8: =IFERROR(__xludf.DUMMYFUNCTION("""COMPUTED_VALUE"""),-680184.237) -> -680184.24 | G8: =IFERROR(__xludf.DUMMYFUNCTION("""COMPUTED_VALUE"""),-680098.9770000001) -> -680098.98 | H8: =IFERROR(__xludf.DUMMYFUNCTION("""COMPUTED_VALUE"""),-712014.3260000001) -> -712014.33 | I8: =IFERROR(__xludf.DUMMYFUNCTION("""COMPUTED_VALUE"""),-711932.7199999999) -> -711932.72 | J8: =IFERROR(__xludf.DUMMYFUNCTION("""COMPUTED_VALUE"""),-711850.2005) -> -711850.2 | K8: =IFERROR(__xludf.DUMMYFUNCTION("""COMPUTED_VALUE"""),-743773.4664999999) -> -743773.47 | L8: =IFERROR(__xludf.DUMMYFUNCTION("""COMPUTED_VALUE"""),-743694.601) -> -743694.6 | M8: =IFERROR(__xludf.DUMMYFUNCTION("""COMPUTED_VALUE"""),-743619.9985) -> -743620 | N8: =IFERROR(__xludf.DUMMYFUNCTION("""COMPUTED_VALUE"""),-754545.396) -> -754545.4 | O8: =IFERROR(__xludf.DUMMYFUNCTION("""COMPUTED_VALUE"""),-754476.5789999999) -> -754476.58 | P8: =IFERROR(__xludf.DUMMYFUNCTION("""COMPUTED_VALUE"""),-754406.2395000001) -> -754406.24 | Q8: =IFERROR(__xludf.DUMMYFUNCTION("""COMPUTED_VALUE"""),-786338.0315) -> -786338.03 | R8: =IFERROR(__xludf.DUMMYFUNCTION("""COMPUTED_VALUE"""),-786268.3010000001) -> -786268.3 | S8: =IFERROR(__xludf.DUMMYFUNCTION("""COMPUTED_VALUE"""),-786204.3559999999) -> -786204.36 | T8: =IFERROR(__xludf.DUMMYFUNCTION("""COMPUTED_VALUE"""),-818140.4110000001) -> -818140.41 | U8: =IFERROR(__xludf.DUMMYFUNCTION("""COMPUTED_VALUE"""),-818080.1199999999) -> -818080.12 | V8: =IFERROR(__xludf.DUMMYFUNCTION("""COMPUTED_VALUE"""),-818018.3065) -> -818018.31 | W8: =IFERROR(__xludf.DUMMYFUNCTION("""COMPUTED_VALUE"""),-849960.756) -> -849960.76 | X8: =IFERROR(__xludf.DUMMYFUNCTION("""COMPUTED_VALUE"""),-849899.5515000001) -> -849899.55 | Y8: =IFERROR(__xludf.DUMMYFUNCTION("""COMPUTED_VALUE"""),-849843.5235000001) -> -849843.52 | Z8: =IFERROR(__xludf.DUMMYFUNCTION("""COMPUTED_VALUE"""),-860788.1044999999) -> -860788.1 | AA8: =IFERROR(__xludf.DUMMYFUNCTION("""COMPUTED_VALUE"""),-860733.2945) -> -860733.29 | AB8: =IFERROR(__xludf.DUMMYFUNCTION("""COMPUTED_VALUE"""),-860683.6610000001) -> -860683.66 | AC8: =IFERROR(__xludf.DUMMYFUNCTION("""COMPUTED_VALUE"""),-892630.3735) -> -892630.37 | AD8: =IFERROR(__xludf.DUMMYFUNCTION("""COMPUTED_VALUE"""),-892577.6949999998) -> -892577.69 | AE8: =IFERROR(__xludf.DUMMYFUNCTION("""COMPUTED_VALUE"""),-892528.6705) -> -892528.67 | AF8: =IFERROR(__xludf.DUMMYFUNCTION("""COMPUTED_VALUE"""),-924481.1684999999) -> -924481.17 | AG8: =IFERROR(__xludf.DUMMYFUNCTION("""COMPUTED_VALUE"""),-924434.2754999999) -> -924434.28 | AH8: =IFERROR(__xludf.DUMMYFUNCTION("""COMPUTED_VALUE"""),-924389.514) -> -924389.51 | AI8: =IFERROR(__xludf.DUMMYFUNCTION("""COMPUTED_VALUE"""),-956343.23) -> -956343.23 | AJ8: =IFERROR(__xludf.DUMMYFUNCTION("""COMPUTED_VALUE"""),-956298.4685) -> -956298.47 | AK8: =IFERROR(__xludf.DUMMYFUNCTION("""COMPUTED_VALUE"""),-956257.361) -> -956257.36 | AL8: =IFERROR(__xludf.DUMMYFUNCTION("""COMPUTED_VALUE"""),-967214.7309999999) -> -967214.73
A9: =IFERROR(__xludf.DUMMYFUNCTION("""COMPUTED_VALUE"""),"Operating Margin %") -> Operating Margin % | B9: =IFERROR(__xludf.DUMMYFUNCTION("""COMPUTED_VALUE"""),-1.3283985813160182) -> -1.3283986 | C9: =IFERROR(__xludf.DUMMYFUNCTION("""COMPUTED_VALUE"""),-1.319336029534819) -> -1.319336 | D9: =IFERROR(__xludf.DUMMYFUNCTION("""COMPUTED_VALUE"""),-1.3105956399337944) -> -1.3105956 | E9: =IFERROR(__xludf.DUMMYFUNCTION("""COMPUTED_VALUE"""),-1.3662354313477871) -> -1.3662354 | F9: =IFERROR(__xludf.DUMMYFUNCTION("""COMPUTED_VALUE"""),-1.3575130674388185) -> -1.3575131 | G9: =IFERROR(__xludf.DUMMYFUNCTION("""COMPUTED_VALUE"""),-1.349306875133603) -> -1.3493069 | H9: =IFERROR(__xludf.DUMMYFUNCTION("""COMPUTED_VALUE"""),-1.4043714125516602) -> -1.4043714 | I9: =IFERROR(__xludf.DUMMYFUNCTION("""COMPUTED_VALUE"""),-1.3963440571707864) -> -1.3963441 | J9: =IFERROR(__xludf.DUMMYFUNCTION("""COMPUTED_VALUE"""),-1.388317782584182) -> -1.3883178 | K9: =IFERROR(__xludf.DUMMYFUNCTION("""COMPUTED_VALUE"""),-1.4430191919523063) -> -1.4430192 | L9: =IFERROR(__xludf.DUMMYFUNCTION("""COMPUTED_VALUE"""),-1.4351803130350334) -> -1.4351803 | M9: =IFERROR(__xludf.DUMMYFUNCTION("""COMPUTED_VALUE"""),-1.4278416350582068) -> -1.4278416 | N9: =IFERROR(__xludf.DUMMYFUNCTION("""COMPUTED_VALUE"""),-1.4415921602279995) -> -1.4415922 | O9: =IFERROR(__xludf.DUMMYFUNCTION("""COMPUTED_VALUE"""),-1.4348578586537835) -> -1.4348579 | P9: =IFERROR(__xludf.DUMMYFUNCTION("""COMPUTED_VALUE"""),-1.428038028410103) -> -1.428038 | Q9: =IFERROR(__xludf.DUMMYFUNCTION("""COMPUTED_VALUE"""),-1.4817865437459525) -> -1.4817865 | R9: =IFERROR(__xludf.DUMMYFUNCTION("""COMPUTED_VALUE"""),-1.4748721465674972) -> -1.4748721 | S9: =IFERROR(__xludf.DUMMYFUNCTION("""COMPUTED_VALUE"""),-1.4685868473403274) -> -1.4685868 | T9: =IFERROR(__xludf.DUMMYFUNCTION("""COMPUTED_VALUE"""),-1.521879284288513) -> -1.5218793 | U9: =IFERROR(__xludf.DUMMYFUNCTION("""COMPUTED_VALUE"""),-1.5158170954823065) -> -1.5158171 | V9: =IFERROR(__xludf.DUMMYFUNCTION("""COMPUTED_VALUE"""),-1.5096508411231442) -> -1.5096508 | W9: =IFERROR(__xludf.DUMMYFUNCTION("""COMPUTED_VALUE"""),-1.5627911517813498) -> -1.5627912 | X9: =IFERROR(__xludf.DUMMYFUNCTION("""COMPUTED_VALUE"""),-1.5565478344145958) -> -1.5565478 | Y9: =IFERROR(__xludf.DUMMYFUNCTION("""COMPUTED_VALUE"""),-1.550875353632181) -> -1.5508754 | Z9: =IFERROR(__xludf.DUMMYFUNCTION("""COMPUTED_VALUE"""),-1.5653073712752952) -> -1.5653074 | AA9: =IFERROR(__xludf.DUMMYFUNCTION("""COMPUTED_VALUE"""),-1.5597665500162439) -> -1.5597665 | AB9: =IFERROR(__xludf.DUMMYFUNCTION("""COMPUTED_VALUE"""),-1.5547821618427087) -> -1.5547822 | AC9: =IFERROR(__xludf.DUMMYFUNCTION("""COMPUTED_VALUE"""),-1.6070778324330983) -> -1.6070778 | AD9: =IFERROR(__xludf.DUMMYFUNCTION("""COMPUTED_VALUE"""),-1.6016663326787706) -> -1.6016663 | AE9: =IFERROR(__xludf.DUMMYFUNCTION("""COMPUTED_VALUE"""),-1.5966622664157586) -> -1.5966623 | AF9: =IFERROR(__xludf.DUMMYFUNCTION("""COMPUTED_VALUE"""),-1.648918503913882) -> -1.6489185 | AG9: =IFERROR(__xludf.DUMMYFUNCTION("""COMPUTED_VALUE"""),-1.6440222083621918) -> -1.6440222 | AH9: =IFERROR(__xludf.DUMMYFUNCTION("""COMPUTED_VALUE"""),-1.6393750611513873) -> -1.6393751 | AI9: =IFERROR(__xludf.DUMMYFUNCTION("""COMPUTED_VALUE"""),-1.6911853226674816) -> -1.6911853 | AJ9: =IFERROR(__xludf.DUMMYFUNCTION("""COMPUTED_VALUE"""),-1.6864339883988302) -> -1.686434 | AK9: =IFERROR(__xludf.DUMMYFUNCTION("""COMPUTED_VALUE"""),-1.6820935862524733) -> -1.6820936 | AL9: =IFERROR(__xludf.DUMMYFUNCTION("""COMPUTED_VALUE"""),-1.6969143463334868) -> -1.6969143
A10: =IFERROR(__xludf.DUMMYFUNCTION("""COMPUTED_VALUE"""),"EBTIDA") -> EBTIDA | B10: =IFERROR(__xludf.DUMMYFUNCTION("""COMPUTED_VALUE"""),-648550.855) -> -648550.85 | C10: =IFERROR(__xludf.DUMMYFUNCTION("""COMPUTED_VALUE"""),-648457.0689999999) -> -648457.07 | D10: =IFERROR(__xludf.DUMMYFUNCTION("""COMPUTED_VALUE"""),-648365.4145000001) -> -648365.41 | E10: =IFERROR(__xludf.DUMMYFUNCTION("""COMPUTED_VALUE"""),-680273.76) -> -680273.76 | F10: =IFERROR(__xludf.DUMMYFUNCTION("""COMPUTED_VALUE"""),-680184.237) -> -680184.24 | G10: =IFERROR(__xludf.DUMMYFUNCTION("""COMPUTED_VALUE"""),-680098.9770000001) -> -680098.98 | H10: =IFERROR(__xludf.DUMMYFUNCTION("""COMPUTED_VALUE"""),-712014.3260000001) -> -712014.33 | I10: =IFERROR(__xludf.DUMMYFUNCTION("""COMPUTED_VALUE"""),-711932.7199999999) -> -711932.72 | J10: =IFERROR(__xludf.DUMMYFUNCTION("""COMPUTED_VALUE"""),-711850.2005) -> -711850.2 | K10: =IFERROR(__xludf.DUMMYFUNCTION("""COMPUTED_VALUE"""),-743773.4664999999) -> -743773.47 | L10: =IFERROR(__xludf.DUMMYFUNCTION("""COMPUTED_VALUE"""),-743694.601) -> -743694.6 | M10: =IFERROR(__xludf.DUMMYFUNCTION("""COMPUTED_VALUE"""),-743619.9985) -> -743620 | N10: =IFERROR(__xludf.DUMMYFUNCTION("""COMPUTED_VALUE"""),-754545.396) -> -754545.4 | O10: =IFERROR(__xludf.DUMMYFUNCTION("""COMPUTED_VALUE"""),-754476.5789999999) -> -754476.58 | P10: =IFERROR(__xludf.DUMMYFUNCTION("""COMPUTED_VALUE"""),-754406.2395000001) -> -754406.24 | Q10: =IFERROR(__xludf.DUMMYFUNCTION("""COMPUTED_VALUE"""),-786338.0315) -> -786338.03 | R10: =IFERROR(__xludf.DUMMYFUNCTION("""COMPUTED_VALUE"""),-786268.3010000001) -> -786268.3 | S10: =IFERROR(__xludf.DUMMYFUNCTION("""COMPUTED_VALUE"""),-786204.3559999999) -> -786204.36 | T10: =IFERROR(__xludf.DUMMYFUNCTION("""COMPUTED_VALUE"""),-818140.4110000001) -> -818140.41 | U10: =IFERROR(__xludf.DUMMYFUNCTION("""COMPUTED_VALUE"""),-818080.1199999999) -> -818080.12 | V10: =IFERROR(__xludf.DUMMYFUNCTION("""COMPUTED_VALUE"""),-818018.3065) -> -818018.31 | W10: =IFERROR(__xludf.DUMMYFUNCTION("""COMPUTED_VALUE"""),-849960.756) -> -849960.76 | X10: =IFERROR(__xludf.DUMMYFUNCTION("""COMPUTED_VALUE"""),-849899.5515000001) -> -849899.55 | Y10: =IFERROR(__xludf.DUMMYFUNCTION("""COMPUTED_VALUE"""),-849843.5235000001) -> -849843.52 | Z10: =IFERROR(__xludf.DUMMYFUNCTION("""COMPUTED_VALUE"""),-860788.1044999999) -> -860788.1 | AA10: =IFERROR(__xludf.DUMMYFUNCTION("""COMPUTED_VALUE"""),-860733.2945) -> -860733.29 | AB10: =IFERROR(__xludf.DUMMYFUNCTION("""COMPUTED_VALUE"""),-860683.6610000001) -> -860683.66 | AC10: =IFERROR(__xludf.DUMMYFUNCTION("""COMPUTED_VALUE"""),-892630.3735) -> -892630.37 | AD10: =IFERROR(__xludf.DUMMYFUNCTION("""COMPUTED_VALUE"""),-892577.6949999998) -> -892577.69 | AE10: =IFERROR(__xludf.DUMMYFUNCTION("""COMPUTED_VALUE"""),-892528.6705) -> -892528.67 | AF10: =IFERROR(__xludf.DUMMYFUNCTION("""COMPUTED_VALUE"""),-924481.1684999999) -> -924481.17 | AG10: =IFERROR(__xludf.DUMMYFUNCTION("""COMPUTED_VALUE"""),-924434.2754999999) -> -924434.28 | AH10: =IFERROR(__xludf.DUMMYFUNCTION("""COMPUTED_VALUE"""),-924389.514) -> -924389.51 | AI10: =IFERROR(__xludf.DUMMYFUNCTION("""COMPUTED_VALUE"""),-956343.23) -> -956343.23 | AJ10: =IFERROR(__xludf.DUMMYFUNCTION("""COMPUTED_VALUE"""),-956298.4685) -> -956298.47 | AK10: =IFERROR(__xludf.DUMMYFUNCTION("""COMPUTED_VALUE"""),-956257.361) -> -956257.36 | AL10: =IFERROR(__xludf.DUMMYFUNCTION("""COMPUTED_VALUE"""),-967214.7309999999) -> -967214.73
A11: =IFERROR(__xludf.DUMMYFUNCTION("""COMPUTED_VALUE"""),"EBTIDA Margin %") -> EBTIDA Margin % | B11: =IFERROR(__xludf.DUMMYFUNCTION("""COMPUTED_VALUE"""),-1.3283985813160182) -> -1.3283986 | C11: =IFERROR(__xludf.DUMMYFUNCTION("""COMPUTED_VALUE"""),-1.319336029534819) -> -1.319336 | D11: =IFERROR(__xludf.DUMMYFUNCTION("""COMPUTED_VALUE"""),-1.3105956399337944) -> -1.3105956 | E11: =IFERROR(__xludf.DUMMYFUNCTION("""COMPUTED_VALUE"""),-1.3662354313477871) -> -1.3662354 | F11: =IFERROR(__xludf.DUMMYFUNCTION("""COMPUTED_VALUE"""),-1.3575130674388185) -> -1.3575131 | G11: =IFERROR(__xludf.DUMMYFUNCTION("""COMPUTED_VALUE"""),-1.349306875133603) -> -1.3493069 | H11: =IFERROR(__xludf.DUMMYFUNCTION("""COMPUTED_VALUE"""),-1.4043714125516602) -> -1.4043714 | I11: =IFERROR(__xludf.DUMMYFUNCTION("""COMPUTED_VALUE"""),-1.3963440571707864) -> -1.3963441 | J11: =IFERROR(__xludf.DUMMYFUNCTION("""COMPUTED_VALUE"""),-1.388317782584182) -> -1.3883178 | K11: =IFERROR(__xludf.DUMMYFUNCTION("""COMPUTED_VALUE"""),-1.4430191919523063) -> -1.4430192 | L11: =IFERROR(__xludf.DUMMYFUNCTION("""COMPUTED_VALUE"""),-1.4351803130350334) -> -1.4351803 | M11: =IFERROR(__xludf.DUMMYFUNCTION("""COMPUTED_VALUE"""),-1.4278416350582068) -> -1.4278416 | N11: =IFERROR(__xludf.DUMMYFUNCTION("""COMPUTED_VALUE"""),-1.4415921602279995) -> -1.4415922 | O11: =IFERROR(__xludf.DUMMYFUNCTION("""COMPUTED_VALUE"""),-1.4348578586537835) -> -1.4348579 | P11: =IFERROR(__xludf.DUMMYFUNCTION("""COMPUTED_VALUE"""),-1.428038028410103) -> -1.428038 | Q11: =IFERROR(__xludf.DUMMYFUNCTION("""COMPUTED_VALUE"""),-1.4817865437459525) -> -1.4817865 | R11: =IFERROR(__xludf.DUMMYFUNCTION("""COMPUTED_VALUE"""),-1.4748721465674972) -> -1.4748721 | S11: =IFERROR(__xludf.DUMMYFUNCTION("""COMPUTED_VALUE"""),-1.4685868473403274) -> -1.4685868 | T11: =IFERROR(__xludf.DUMMYFUNCTION("""COMPUTED_VALUE"""),-1.521879284288513) -> -1.5218793 | U11: =IFERROR(__xludf.DUMMYFUNCTION("""COMPUTED_VALUE"""),-1.5158170954823065) -> -1.5158171 | V11: =IFERROR(__xludf.DUMMYFUNCTION("""COMPUTED_VALUE"""),-1.5096508411231442) -> -1.5096508 | W11: =IFERROR(__xludf.DUMMYFUNCTION("""COMPUTED_VALUE"""),-1.5627911517813498) -> -1.5627912 | X11: =IFERROR(__xludf.DUMMYFUNCTION("""COMPUTED_VALUE"""),-1.5565478344145958) -> -1.5565478 | Y11: =IFERROR(__xludf.DUMMYFUNCTION("""COMPUTED_VALUE"""),-1.550875353632181) -> -1.5508754 | Z11: =IFERROR(__xludf.DUMMYFUNCTION("""COMPUTED_VALUE"""),-1.5653073712752952) -> -1.5653074 | AA11: =IFERROR(__xludf.DUMMYFUNCTION("""COMPUTED_VALUE"""),-1.5597665500162439) -> -1.5597665 | AB11: =IFERROR(__xludf.DUMMYFUNCTION("""COMPUTED_VALUE"""),-1.5547821618427087) -> -1.5547822 | AC11: =IFERROR(__xludf.DUMMYFUNCTION("""COMPUTED_VALUE"""),-1.6070778324330983) -> -1.6070778 | AD11: =IFERROR(__xludf.DUMMYFUNCTION("""COMPUTED_VALUE"""),-1.6016663326787706) -> -1.6016663 | AE11: =IFERROR(__xludf.DUMMYFUNCTION("""COMPUTED_VALUE"""),-1.5966622664157586) -> -1.5966623 | AF11: =IFERROR(__xludf.DUMMYFUNCTION("""COMPUTED_VALUE"""),-1.648918503913882) -> -1.6489185 | AG11: =IFERROR(__xludf.DUMMYFUNCTION("""COMPUTED_VALUE"""),-1.6440222083621918) -> -1.6440222 | AH11: =IFERROR(__xludf.DUMMYFUNCTION("""COMPUTED_VALUE"""),-1.6393750611513873) -> -1.6393751 | AI11: =IFERROR(__xludf.DUMMYFUNCTION("""COMPUTED_VALUE"""),-1.6911853226674816) -> -1.6911853 | AJ11: =IFERROR(__xludf.DUMMYFUNCTION("""COMPUTED_VALUE"""),-1.6864339883988302) -> -1.686434 | AK11: =IFERROR(__xludf.DUMMYFUNCTION("""COMPUTED_VALUE"""),-1.6820935862524733) -> -1.6820936 | AL11: =IFERROR(__xludf.DUMMYFUNCTION("""COMPUTED_VALUE"""),-1.6969143463334868) -> -1.6969143

Sheet Budget_Long
A1: Month | B1: Account | C1: Category | D1: Budget_Amount
A2: 45658 | B2: Subscription Revenue | C2: Revenue | D2: 456923
A3: 45659 | B3: COGS | C3: COGS | D3: -91385
A4: 45660 | B4: Sales & Marketing Expense | C4: Opex | D4: -159923
A5: 45661 | B5: R&D Expense | C5: Opex | D5: -68538
A6: 45662 | B6: G&A Expense | C6: Opex | D6: -54831
A7: 45663 | B7: EBTIDA | C7: Opex | D7: -648792
A8: 45689 | B8: Subscription Revenue | C8: Revenue | D8: 452111
A9: 45690 | B9: COGS | C9: COGS | D9: -90422
A10: 45691 | B10: Sales & Marketing Expense | C10: Opex | D10: -158239
A11: 45692 | B11: R&D Expense | C11: Opex | D11: -67817
A12: 45693 | B12: G&A Expense | C12: Opex | D12: -54253
A13: 45694 | B13: EBTIDA | C13: Opex | D13: -648937
... A25: 45753 | B25: EBTIDA | C25: Opex | D25: -681205

Sheet Actuals_Long
A1: Month | B1: Account | C1: Category | D1: Actual_Amount
A2: 45658 | B2: Subscription Revenue | C2: Revenue | D2: 448000
A3: 45659 | B3: COGS | C3: COGS | D3: -93500
A4: 45660 | B4: Sales & Marketing Expense | C4: Opex | D4: -172000
A5: 45661 | B5: R&D Expense | C5: Opex | D5: -69800
A6: 45662 | B6: G&A Expense | C6: Opex | D6: -56000
A7: 45663 | B7: EBTIDA | C7: Opex | D7: -694300
A8: 45689 | B8: Subscription Revenue | C8: Revenue | D8: 460500
A9: 45690 | B9: COGS | C9: COGS | D9: -91200
A10: 45691 | B10: Sales & Marketing Expense | C10: Opex | D10: -165500
A11: 45692 | B11: R&D Expense | C11: Opex | D11: -68400
A12: 45693 | B12: G&A Expense | C12: Opex | D12: -55100
A13: 45694 | B13: EBTIDA | C13: Opex | D13: -668000
... A25: 45753 | B25: EBTIDA | C25: Opex | D25: -706000

Sheet Variance_Calc
A1: Month | B1: Account | C1: Budget | D1: Actual | E1: $ Variance | F1: % Variance | G1: Driver
A2: 45658 | B2: Subscription Revenue | C2: =SUMIFS(Budget_Long!D:D, Budget_Long!A:A, A2, Budget_Long!B:B, B2) -> 456923 | D2: =SUMIFS(Actuals_Long!D:D, Actuals_Long!A:A, A2, Actuals_Long!B:B, B2) -> 448000 | E2: =D2-C2 -> -8923 | F2: =IF(C2=0,"",(D2-C2)/ABS(C2)) -> -0.019528454 | G2: Slower new customer acquistion
A3: 45659 | B3: COGS | C3: =SUMIFS(Budget_Long!D:D, Budget_Long!A:A, A3, Budget_Long!B:B, B3) -> -91385 | D3: =SUMIFS(Actuals_Long!D:D, Actuals_Long!A:A, A3, Actuals_Long!B:B, B3) -> -93500 | E3: =D3-C3 -> -2115 | F3: =IF(C3=0,"",(D3-C3)/ABS(C3)) -> -0.023143842
A4: 45660 | B4: Sales & Marketing Expense | C4: =SUMIFS(Budget_Long!D:D, Budget_Long!A:A, A4, Budget_Long!B:B, B4) -> -159923 | D4: =SUMIFS(Actuals_Long!D:D, Actuals_Long!A:A, A4, Actuals_Long!B:B, B4) -> -172000 | E4: =D4-C4 -> -12077 | F4: =IF(C4=0,"",(D4-C4)/ABS(C4)) -> -0.075517593 | G4: Front-loaded growth campaign spend
A5: 45661 | B5: R&D Expense | C5: =SUMIFS(Budget_Long!D:D, Budget_Long!A:A, A5, Budget_Long!B:B, B5) -> -68538 | D5: =SUMIFS(Actuals_Long!D:D, Actuals_Long!A:A, A5, Actuals_Long!B:B, B5) -> -69800 | E5: =D5-C5 -> -1262 | F5: =IF(C5=0,"",(D5-C5)/ABS(C5)) -> -0.018413143
A6: 45662 | B6: G&A Expense | C6: =SUMIFS(Budget_Long!D:D, Budget_Long!A:A, A6, Budget_Long!B:B, B6) -> -54831 | D6: =SUMIFS(Actuals_Long!D:D, Actuals_Long!A:A, A6, Actuals_Long!B:B, B6) -> -56000 | E6: =D6-C6 -> -1169 | F6: =IF(C6=0,"",(D6-C6)/ABS(C6)) -> -0.021320056
A7: 45663 | B7: EBTIDA | C7: =SUMIFS(Budget_Long!D:D, Budget_Long!A:A, A7, Budget_Long!B:B, B7) -> -648792 | D7: =SUMIFS(Actuals_Long!D:D, Actuals_Long!A:A, A7, Actuals_Long!B:B, B7) -> -694300 | E7: =D7-C7 -> -45508 | F7: =IF(C7=0,"",(D7-C7)/ABS(C7)) -> -0.070142665 | G7: Driven by S&M overspend and revenue miss
A8: 45689 | B8: Subscription Revenue | C8: =SUMIFS(Budget_Long!D:D, Budget_Long!A:A, A8, Budget_Long!B:B, B8) -> 452111 | D8: =SUMIFS(Actuals_Long!D:D, Actuals_Long!A:A, A8, Actuals_Long!B:B, B8) -> 460500 | E8: =D8-C8 -> 8389 | F8: =IF(C8=0,"",(D8-C8)/ABS(C8)) -> 0.018555178 | G8: Stronger-than-expected expansion revenue
A9: 45690 | B9: COGS | C9: =SUMIFS(Budget_Long!D:D, Budget_Long!A:A, A9, Budget_Long!B:B, B9) -> -90422 | D9: =SUMIFS(Actuals_Long!D:D, Actuals_Long!A:A, A9, Actuals_Long!B:B, B9) -> -91200 | E9: =D9-C9 -> -778 | F9: =IF(C9=0,"",(D9-C9)/ABS(C9)) -> -0.0086041008
A10: 45691 | B10: Sales & Marketing Expense | C10: =SUMIFS(Budget_Long!D:D, Budget_Long!A:A, A10, Budget_Long!B:B, B10) -> -158239 | D10: =SUMIFS(Actuals_Long!D:D, Actuals_Long!A:A, A10, Actuals_Long!B:B, B10) -> -165500 | E10: =D10-C10 -> -7261 | F10: =IF(C10=0,"",(D10-C10)/ABS(C10)) -> -0.045886286 | G10: Elevated paid acquisiton cost
A11: 45692 | B11: R&D Expense | C11: =SUMIFS(Budget_Long!D:D, Budget_Long!A:A, A11, Budget_Long!B:B, B11) -> -67817 | D11: =SUMIFS(Actuals_Long!D:D, Actuals_Long!A:A, A11, Actuals_Long!B:B, B11) -> -68400 | E11: =D11-C11 -> -583 | F11: =IF(C11=0,"",(D11-C11)/ABS(C11)) -> -0.0085966646
A12: 45693 | B12: G&A Expense | C12: =SUMIFS(Budget_Long!D:D, Budget_Long!A:A, A12, Budget_Long!B:B, B12) -> -54253 | D12: =SUMIFS(Actuals_Long!D:D, Actuals_Long!A:A, A12, Actuals_Long!B:B, B12) -> -55100 | E12: =D12-C12 -> -847 | F12: =IF(C12=0,"",(D12-C12)/ABS(C12)) -> -0.01561204
A13: 45694 | B13: EBTIDA | C13: =SUMIFS(Budget_Long!D:D, Budget_Long!A:A, A13, Budget_Long!B:B, B13) -> -648937 | D13: =SUMIFS(Actuals_Long!D:D, Actuals_Long!A:A, A13, Actuals_Long!B:B, B13) -> -668000 | E13: =D13-C13 -> -19063 | F13: =IF(C13=0,"",(D13-C13)/ABS(C13)) -> -0.029375733 | G13: Revenue upside partially offset by higher S&M spend
A14: 45717 | B14: Subscription Revenue | C14: =SUMIFS(Budget_Long!D:D, Budget_Long!A:A, A14, Budget_Long!B:B, B14) -> 447686 | D14: =SUMIFS(Actuals_Long!D:D, Actuals_Long!A:A, A14, Actuals_Long!B:B, B14) -> 442000 | E14: =D14-C14 -> -5686 | F14: =IF(C14=0,"",(D14-C14)/ABS(C14)) -> -0.012700866
A15: 45718 | B15: COGS | C15: =SUMIFS(Budget_Long!D:D, Budget_Long!A:A, A15, Budget_Long!B:B, B15) -> -89537 | D15: =SUMIFS(Actuals_Long!D:D, Actuals_Long!A:A, A15, Actuals_Long!B:B, B15) -> -90800 | E15: =D15-C15 -> -1263 | F15: =IF(C15=0,"",(D15-C15)/ABS(C15)) -> -0.0141059
A16: 45719 | B16: Sales & Marketing Expense | C16: =SUMIFS(Budget_Long!D:D, Budget_Long!A:A, A16, Budget_Long!B:B, B16) -> -156690 | D16: =SUMIFS(Actuals_Long!D:D, Actuals_Long!A:A, A16, Actuals_Long!B:B, B16) -> -158900 | E16: =D16-C16 -> -2210 | F16: =IF(C16=0,"",(D16-C16)/ABS(C16)) -> -0.014104282
A17: 45720 | B17: R&D Expense | C17: =SUMIFS(Budget_Long!D:D, Budget_Long!A:A, A17, Budget_Long!B:B, B17) -> -67153 | D17: =SUMIFS(Actuals_Long!D:D, Actuals_Long!A:A, A17, Actuals_Long!B:B, B17) -> -66900 | E17: =D17-C17 -> 253 | F17: =IF(C17=0,"",(D17-C17)/ABS(C17)) -> 0.003767516
A18: 45721 | B18: G&A Expense | C18: =SUMIFS(Budget_Long!D:D, Budget_Long!A:A, A18, Budget_Long!B:B, B18) -> -53722 | D18: =SUMIFS(Actuals_Long!D:D, Actuals_Long!A:A, A18, Actuals_Long!B:B, B18) -> -54300 | E18: =D18-C18 -> -578 | F18: =IF(C18=0,"",(D18-C18)/ABS(C18)) -> -0.010759093
A19: 45722 | B19: EBTIDA | C19: =SUMIFS(Budget_Long!D:D, Budget_Long!A:A, A19, Budget_Long!B:B, B19) -> -649069 | D19: =SUMIFS(Actuals_Long!D:D, Actuals_Long!A:A, A19, Actuals_Long!B:B, B19) -> -671900 | E19: =D19-C19 -> -22831 | F19: =IF(C19=0,"",(D19-C19)/ABS(C19)) -> -0.035174997
A20: 45748 | B20: Subscription Revenue | C20: =SUMIFS(Budget_Long!D:D, Budget_Long!A:A, A20, Budget_Long!B:B, B20) -> 443159 | D20: =SUMIFS(Actuals_Long!D:D, Actuals_Long!A:A, A20, Actuals_Long!B:B, B20) -> 438200 | E20: =D20-C20 -> -4959 | F20: =IF(C20=0,"",(D20-C20)/ABS(C20)) -> -0.011190115 | G20: Softer new-logo conversion
A21: 45749 | B21: COGS | C21: =SUMIFS(Budget_Long!D:D, Budget_Long!A:A, A21, Budget_Long!B:B, B21) -> -88632 | D21: =SUMIFS(Actuals_Long!D:D, Actuals_Long!A:A, A21, Actuals_Long!B:B, B21) -> -90100 | E21: =D21-C21 -> -1468 | F21: =IF(C21=0,"",(D21-C21)/ABS(C21)) -> -0.016562867
A22: 45750 | B22: Sales & Marketing Expense | C22: =SUMIFS(Budget_Long!D:D, Budget_Long!A:A, A22, Budget_Long!B:B, B22) -> -155106 | D22: =SUMIFS(Actuals_Long!D:D, Actuals_Long!A:A, A22, Actuals_Long!B:B, B22) -> -162800 | E22: =D22-C22 -> -7694 | F22: =IF(C22=0,"",(D22-C22)/ABS(C22)) -> -0.049604786 | G22: Continued investment in demand generation
A23: 45751 | B23: R&D Expense | C23: =SUMIFS(Budget_Long!D:D, Budget_Long!A:A, A23, Budget_Long!B:B, B23) -> -66474 | D23: =SUMIFS(Actuals_Long!D:D, Actuals_Long!A:A, A23, Actuals_Long!B:B, B23) -> -67900 | E23: =D23-C23 -> -1426 | F23: =IF(C23=0,"",(D23-C23)/ABS(C23)) -> -0.021451996
A24: 45752 | B24: G&A Expense | C24: =SUMIFS(Budget_Long!D:D, Budget_Long!A:A, A24, Budget_Long!B:B, B24) -> -53179 | D24: =SUMIFS(Actuals_Long!D:D, Actuals_Long!A:A, A24, Actuals_Long!B:B, B24) -> -55400 | E24: =D24-C24 -> -2221 | F24: =IF(C24=0,"",(D24-C24)/ABS(C24)) -> -0.041764606
A25: 45753 | B25: EBTIDA | C25: =SUMIFS(Budget_Long!D:D, Budget_Long!A:A, A25, Budget_Long!B:B, B25) -> -681205 | D25: =SUMIFS(Actuals_Long!D:D, Actuals_Long!A:A, A25, Actuals_Long!B:B, B25) -> -706000 | E25: =D25-C25 -> -24795 | F25: =IF(C25=0,"",(D25-C25)/ABS(C25)) -> -0.036398735 | G25: Unfavorable variance driven by revenue softness and S&M overspend

Sheet Monthly_Summary
A1: Month | B1: Commentary | C1: Revenue % Variance | D1: S&M % Variance | E1: EBTIDA % Variance
A2: 45658 | B2: =TEXTJOIN(" ", TRUE, "Revenue was", IF(C2>0,"above","below"), "plan by", TEXT(ABS(C2),"0.0%")&".", "Sales & Marketing spend was", IF(D2<0,"above","below"), "budget by", TEXT(ABS(D2),"0.0%")&".", "EBITDA was", IF(E2<0,"below","above"), "plan by", TEXT(ABS(E2),"0.0%")&"." ) -> Revenue was below plan by 2.0%. Sales & Marketing spend was above budget by 7.6%. EBITDA was below plan by 7.0%. | C2: =Variance_Calc!F2 -> -0.019528454 | D2: =Variance_Calc!F4 -> -0.075517593 | E2: =Variance_Calc!F7 -> -0.070142665
A3: 45689 | B3: =TEXTJOIN(" ", TRUE, "Revenue was", IF(C3>0,"above","below"), "plan by", TEXT(ABS(C3),"0.0%")&".", "Sales & Marketing spend was", IF(D3<0,"above","below"), "budget by", TEXT(ABS(D3),"0.0%")&".", "EBITDA was", IF(E3<0,"below","above"), "plan by", TEXT(ABS(E3),"0.0%")&"." ) -> Revenue was above plan by 1.9%. Sales & Marketing spend was above budget by 4.6%. EBITDA was below plan by 2.9%. | C3: =Variance_Calc!F8 -> 0.018555178 | D3: =Variance_Calc!F10 -> -0.045886286 | E3: =Variance_Calc!F13 -> -0.029375733
A4: 45717 | B4: =TEXTJOIN(" ", TRUE, "Revenue was", IF(C4>0,"above","below"), "plan by", TEXT(ABS(C4),"0.0%")&".", "Sales & Marketing spend was", IF(D4<0,"above","below"), "budget by", TEXT(ABS(D4),"0.0%")&".", "EBITDA was", IF(E4<0,"below","above"), "plan by", TEXT(ABS(E4),"0.0%")&"." ) -> Revenue was below plan by 1.3%. Sales & Marketing spend was above budget by 1.4%. EBITDA was below plan by 3.5%. | C4: =Variance_Calc!F14 -> -0.012700866 | D4: =Variance_Calc!F16 -> -0.014104282 | E4: =Variance_Calc!F19 -> -0.035174997
A5: 45748 | B5: =TEXTJOIN(" ", TRUE, "Revenue was", IF(C5>0,"above","below"), "plan by", TEXT(ABS(C5),"0.0%")&".", "Sales & Marketing spend was", IF(D5<0,"above","below"), "budget by", TEXT(ABS(D5),"0.0%")&".", "EBITDA was", IF(E5<0,"below","above"), "plan by", TEXT(ABS(E5),"0.0%")&"." ) -> Revenue was below plan by 1.1%. Sales & Marketing spend was above budget by 5.0%. EBITDA was below plan by 3.6%. | C5: =Variance_Calc!F20 -> -0.011190115 | D5: =Variance_Calc!F22 -> -0.049604786 | E5: =Variance_Calc!F25 -> -0.036398735
